README.txt
setup.cfg
setup.py
docs/HISTORY.txt
docs/INSTALL.txt
docs/LICENSE.GPL
docs/LICENSE.txt
experimental/__init__.py
experimental.daterangeindexoptimisations.egg-info/PKG-INFO
experimental.daterangeindexoptimisations.egg-info/SOURCES.txt
experimental.daterangeindexoptimisations.egg-info/dependency_links.txt
experimental.daterangeindexoptimisations.egg-info/entry_points.txt
experimental.daterangeindexoptimisations.egg-info/namespace_packages.txt
experimental.daterangeindexoptimisations.egg-info/not-zip-safe
experimental.daterangeindexoptimisations.egg-info/requires.txt
experimental.daterangeindexoptimisations.egg-info/top_level.txt
experimental/daterangeindexoptimisations/__init__.py
experimental/daterangeindexoptimisations/configure.zcml
experimental/daterangeindexoptimisations/patches.py
experimental/daterangeindexoptimisations/tests.py