Metadata-Version: 1.0
Name: experimental.daterangeindexoptimisations
Version: 1.1
Summary: A patch to Zope2's DateRangeIndexes to store data more efficiently
Home-page: https://svn.plone.org/svn/collective/experimental.daterangeindexoptimisations
Author: Matt Hamilton
Author-email: matth@netsight.co.uk
License: GPL
Keywords: plone performance indexing daterangeindex catalog speedups
Platform: UNKNOWN
Classifier: Framework :: Plone
Classifier: Programming Language :: Python
Classifier: Topic :: Software Development :: Libraries :: Python Modules
